xbmcext.py
xbmcext-1.3.0.dist-info/METADATA
xbmcext-1.3.0.dist-info/WHEEL
xbmcext-1.3.0.dist-info/licenses/LICENSE
xbmcext-1.3.0.dist-info/RECORD
